magnet_data/__init__.py
magnet_data/admin.py
magnet_data/apps.py
magnet_data/currencies/__init__.py
magnet_data/currencies/client.py
magnet_data/currencies/currency_pair.py
magnet_data/currencies/enums.py
magnet_data/currencies/exceptions.py
magnet_data/currencies/models.py
magnet_data/currencies/urls.py
magnet_data/holidays/__init__.py
magnet_data/holidays/enums.py
magnet_data/holidays/models.py
magnet_data/magnet_data_client.py
magnet_data/migrations/0001_initial.py
magnet_data/migrations/0002_holiday.py
magnet_data/migrations/0003_alter_holiday_unique_together.py
magnet_data/migrations/__init__.py
magnet_data/models.py
magnet_data/utils.py
django_magnet_data-1.3.0.dist-info/LICENSE
django_magnet_data-1.3.0.dist-info/METADATA
django_magnet_data-1.3.0.dist-info/WHEEL
django_magnet_data-1.3.0.dist-info/RECORD
