Metadata-Version: 2.1
Name: django_magnet_data
Version: 1.3.0
Summary: An API client for data.magnet.cl
Home-page: https://github.com/magnet-cl/django-magnet-data
License: MIT
Author: Ignacio Munizaga
Author-email: muni@magnet.cl
Requires-Python: >=3.6.2,<4.0.0
Classifier: Framework :: Django
Classifier: Framework :: Django :: 2.2
Classifier: Framework :: Django :: 3.2
Classifier: Framework :: Django :: 4.0
Classifier: License :: OSI Approved :: MIT License
Classifier: Operating System :: OS Independent
Classifier: Programming Language :: Python :: 3
Classifier: Programming Language :: Python :: 3.7
Classifier: Programming Language :: Python :: 3.8
Classifier: Programming Language :: Python :: 3.9
Classifier: Programming Language :: Python :: 3.10
Classifier: Programming Language :: Python :: 3.11
Classifier: Programming Language :: Python :: 3.12
Requires-Dist: django (>=2.2)
Project-URL: Repository, https://github.com/magnet-cl/django-magnet-data
